README.md
setup.py
pyprooff/__init__.py
pyprooff/conts.py
pyprooff/err.py
pyprooff/h2o.py
pyprooff/inout.py
pyprooff/kmedoids.py
pyprooff/nlp.py
pyprooff/pd.py
pyprooff/pdevaluators.py
pyprooff/pdf.py
pyprooff/pdpar.py
pyprooff/pdprofiler.py
pyprooff/perf.py
pyprooff/pprint.py
pyprooff/similar.py
pyprooff/soup.py
pyprooff/stats.py
pyprooff/to_precision.py
pyprooff/util.py
pyprooff/winclip.py
pyprooff.egg-info/PKG-INFO
pyprooff.egg-info/SOURCES.txt
pyprooff.egg-info/dependency_links.txt
pyprooff.egg-info/top_level.txt