Metadata-Version: 1.1
Name: pyprooff
Version: 0.1
Summary: Handy functions n stuff
Home-page: https://github.com/Prooffreader/pyprooff/
Author: David Taylor
Author-email: prooffreader@gmail.com
License: MIT
Download-URL: https://github.com/Prooffreader/pyprooff/archive/0.1.tar.gz
Keywords: prooffreader
Platform: UNKNOWN
Classifier: Development Status :: 4 - Beta
Classifier: Programming Language :: Python :: 3
